mosaic_model/__init__.py
mosaic_model/logger_config.py
mosaic_model/models/__init__.py
mosaic_model/models/bart_based_model/__init__.py
mosaic_model/models/bart_based_model/tag_sum_extractor.py
mosaic_model/models/base_extractor.py
mosaic_model/models/metrics.py
mosaic_model/models/rake_based_model/__init__.py
mosaic_model/models/rake_based_model/keyphrases_extractor.py
mosaic_model/models/rake_based_model/tags_extractor.py
mosaic_model/models/ygpt_based_model/__init__.py
mosaic_model/models/ygpt_based_model/ygpt_model.py
mosaic_model/processing/__init__.py
mosaic_model/processing/embedder/__init__.py
mosaic_model/processing/embedder/base_embedder.py
mosaic_model/processing/embedder/fasttext_embedder.py
mosaic_model/processing/embedder/hg_embedder.py
mosaic_model/processing/normalizers/__init__.py
mosaic_model/processing/normalizers/base_normalizer.py
mosaic_model/processing/normalizers/nouns_keeper.py
mosaic_model/processing/normalizers/pipe.py
mosaic_model/processing/normalizers/punctuation_deleter.py
mosaic_model/processing/normalizers/stopwords_deleter.py
mosaic_model/processing/ranker/__init__.py
mosaic_model/processing/ranker/base_ranker.py
mosaic_model/processing/ranker/max_distance_ranker.py
mosaic_model/processing/ranker/text_sim_ranker.py
mosaic_model/processing/summarizator/__init__.py
mosaic_model/processing/summarizator/bart_summarization.py
mosaic_model/processing/utils.py
mosaic_model-0.1.4.dist-info/METADATA
mosaic_model-0.1.4.dist-info/WHEEL
mosaic_model-0.1.4.dist-info/RECORD
